genif.cpython-37m-x86_64-linux-gnu.so
genif-1.0.1.dist-info/LICENSE
genif-1.0.1.dist-info/WHEEL
genif-1.0.1.dist-info/METADATA
genif-1.0.1.dist-info/top_level.txt
genif-1.0.1.dist-info/RECORD
genif.libs/libgomp-a34b3233.so.1.0.0
