Metadata-Version: 2.1
Name: genif
Version: 1.0.1
Summary: Generalized Isolation Forest
Home-page: UNKNOWN
Author: Philipp-Jan Honysz
Author-email: philipp.honysz@udo.edu
License: UNKNOWN
Platform: UNKNOWN
